wooty_woot/__init__.py
wooty_woot/_version.py
wooty_woot/handlers.py
wooty_woot/labextension/package.json
wooty_woot/labextension/schemas/wooty_woot/package.json.orig
wooty_woot/labextension/schemas/wooty_woot/plugin.json
wooty_woot/labextension/static/747.c0aa2b756a4afbd24020.js
wooty_woot/labextension/static/763.96045d0f5ec29edf46d4.js
wooty_woot/labextension/static/remoteEntry.087c31728fc1df8903e8.js
wooty_woot/labextension/static/style.js
wooty_woot/labextension/static/third-party-licenses.json
wooty_woot/notebooks/__init__.py
wooty_woot/notebooks/hello.ipynb
wooty_woot/tests/__init__.py
wooty_woot/tests/test_handlers.py
wooty_woot-0.6.0.data/data/etc/jupyter/jupyter_notebook_config.d/wooty_woot.json
wooty_woot-0.6.0.data/data/etc/jupyter/jupyter_server_config.d/wooty_woot.json
wooty_woot-0.6.0.data/data/share/jupyter/labextensions/wooty_woot/install.json
wooty_woot-0.6.0.data/data/share/jupyter/labextensions/wooty_woot/package.json
wooty_woot-0.6.0.data/data/share/jupyter/labextensions/wooty_woot/schemas/wooty_woot/package.json.orig
wooty_woot-0.6.0.data/data/share/jupyter/labextensions/wooty_woot/schemas/wooty_woot/plugin.json
wooty_woot-0.6.0.data/data/share/jupyter/labextensions/wooty_woot/static/747.c0aa2b756a4afbd24020.js
wooty_woot-0.6.0.data/data/share/jupyter/labextensions/wooty_woot/static/763.96045d0f5ec29edf46d4.js
wooty_woot-0.6.0.data/data/share/jupyter/labextensions/wooty_woot/static/remoteEntry.087c31728fc1df8903e8.js
wooty_woot-0.6.0.data/data/share/jupyter/labextensions/wooty_woot/static/style.js
wooty_woot-0.6.0.data/data/share/jupyter/labextensions/wooty_woot/static/third-party-licenses.json
wooty_woot-0.6.0.dist-info/LICENSE
wooty_woot-0.6.0.dist-info/METADATA
wooty_woot-0.6.0.dist-info/WHEEL
wooty_woot-0.6.0.dist-info/top_level.txt
wooty_woot-0.6.0.dist-info/RECORD
